antinex_core/__init__.py
antinex_core/antinex_processor.py
antinex_core/antinex_worker.py
antinex_core/send_results_to_broker.py
antinex_core/log/__init__.py
antinex_core/log/setup_logging.py
antinex_core/scripts/__init__.py
antinex_core/scripts/antinex_scaler_django.py
antinex_core/scripts/convert_bottom_rows_to_json.py
antinex_core/scripts/publish_predict_request.py
antinex_core/scripts/publish_regression_predict.py
antinex_core/scripts/publish_train_request.py
antinex_core/scripts/run_s3_test.py
antinex_core/scripts/standalone_scaler_django.py
antinex_core-1.3.13.data/scripts/antinex_scaler_django.py
antinex_core-1.3.13.data/scripts/convert_bottom_rows_to_json.py
antinex_core-1.3.13.data/scripts/publish_predict_request.py
antinex_core-1.3.13.data/scripts/publish_regression_predict.py
antinex_core-1.3.13.data/scripts/publish_train_request.py
antinex_core-1.3.13.data/scripts/run-antinex-core.sh
antinex_core-1.3.13.data/scripts/run_s3_test.py
antinex_core-1.3.13.data/scripts/standalone_scaler_django.py
antinex_core-1.3.13.data/scripts/update-repos-in-container.sh
antinex_core-1.3.13.dist-info/LICENSE
antinex_core-1.3.13.dist-info/METADATA
antinex_core-1.3.13.dist-info/WHEEL
antinex_core-1.3.13.dist-info/top_level.txt
antinex_core-1.3.13.dist-info/RECORD
