Metadata-Version: 2.1
Name: antinex-core
Version: 1.3.13
Summary: AntiNex publisher-subscriber core for processing training and prediction requests for deep neural networks to detect network exploits using Keras and Tensorflow in near real-time.
Home-page: https://github.com/jay-johnson/antinex-core
Author: Jay Johnson
Author-email: jay.p.h.johnson@gmail.com
License: UNKNOWN
Platform: UNKNOWN
Classifier: Development Status :: 5 - Production/Stable
Classifier: Intended Audience :: Developers
Classifier: License :: OSI Approved :: Apache Software License
Classifier: Operating System :: OS Independent
Classifier: Programming Language :: Python :: 3.5
Classifier: Programming Language :: Python :: 3.6
Classifier: Programming Language :: Python :: Implementation :: PyPy
Classifier: Topic :: Software Development :: Libraries :: Python Modules
Requires-Dist: celery (>=4.1.0)
Requires-Dist: celery-connectors (>=1.0.27)
Requires-Dist: celery-loaders (>=1.0.5)
Requires-Dist: colorlog
Requires-Dist: coverage
Requires-Dist: flake8 (<=3.4.1)
Requires-Dist: future
Requires-Dist: matplotlib
Requires-Dist: numpy (>=1.14.5)
Requires-Dist: pandas
Requires-Dist: pep8 (>=1.7.1)
Requires-Dist: pipenv
Requires-Dist: pycodestyle (<=2.3.1)
Requires-Dist: pylint
Requires-Dist: recommonmark
Requires-Dist: requests
Requires-Dist: scikit-learn
Requires-Dist: seaborn
Requires-Dist: sphinx
Requires-Dist: sphinx-autobuild
Requires-Dist: sphinx-bootstrap-theme
Requires-Dist: sphinx-rtd-theme
Requires-Dist: spylunking
Requires-Dist: tox
Requires-Dist: tqdm
Requires-Dist: unittest2
Requires-Dist: mock
Requires-Dist: antinex-utils
Requires-Dist: h5py
Requires-Dist: keras
Requires-Dist: tables
Requires-Dist: tensorflow
